[{"Uhrzeit":"Thu, 01 Jul 2021 13:19:32 GMT","Herzschlag":"0","Sauerstoff":"","Emotion":""},{"Uhrzeit":"Thu, 01 Jul 2021 13:19:33 GMT","Herzschlag":"0","Sauerstoff":"","Emotion":""},{"Uhrzeit":"Thu, 01 Jul 2021 13:19:33 GMT","Herzschlag":"97","Sauerstoff":"","Emotion":""},{"Uhrzeit":"Thu, 01 Jul 2021 13:19:33 GMT","Herzschlag":"97","Sauerstoff":"","Emotion":""},{"Uhrzeit":"Thu, 01 Jul 2021 13:19:33 GMT","Herzschlag":"97","Sauerstoff":"","Emotion":""},{"Uhrzeit":"Thu, 01 Jul 2021 13:19:34 GMT","Herzschlag":"97","Sauerstoff":"","Emotion":""},{"Uhrzeit":"Thu, 01 Jul 2021 13:19:34 GMT","Herzschlag":"97","Sauerstoff":"","Emotion":""},{"Uhrzeit":"Thu, 01 Jul 2021 13:19:34 GMT","Herzschlag":"97","Sauerstoff":"","Emotion":""},{"Uhrzeit":"Thu, 01 Jul 2021 13:19:35 GMT","Herzschlag":"97","Sauerstoff":"","Emotion":""},{"Uhrzeit":"Thu, 01 Jul 2021 13:19:35 GMT","Herzschlag":"97","Sauerstoff":"","Emotion":""},{"Uhrzeit":"Thu, 01 Jul 2021 13:19:35 GMT","Herzschlag":"97","Sauerstoff":"","Emotion":""},{"Uhrzeit":"Thu, 01 Jul 2021 13:19:35 GMT","Herzschlag":"96","Sauerstoff":"","Emotion":""},{"Uhrzeit":"Thu, 01 Jul 2021 13:19:36 GMT","Herzschlag":"96","Sauerstoff":"","Emotion":""},{"Uhrzeit":"Thu, 01 Jul 2021 13:19:36 GMT","Herzschlag":"96","Sauerstoff":"","Emotion":""},{"Uhrzeit":"Thu, 01 Jul 2021 13:19:36 GMT","Herzschlag":"89","Sauerstoff":"","Emotion":""},{"Uhrzeit":"Thu, 01 Jul 2021 13:19:36 GMT","Herzschlag":"89","Sauerstoff":"","Emotion":""},{"Uhrzeit":"Thu, 01 Jul 2021 13:19:37 GMT","Herzschlag":"89","Sauerstoff":"","Emotion":""},{"Uhrzeit":"Thu, 01 Jul 2021 13:19:37 GMT","Herzschlag":"89","Sauerstoff":"","Emotion":""},{"Uhrzeit":"Thu, 01 Jul 2021 13:19:37 GMT","Herzschlag":"89","Sauerstoff":"","Emotion":""},{"Uhrzeit":"Thu, 01 Jul 2021 13:19:37 GMT","Herzschlag":"89","Sauerstoff":"","Emotion":""},{"Uhrzeit":"Thu, 01 Jul 2021 13:19:38 GMT","Herzschlag":"87","Sauerstoff":"","Emotion":""},{"Uhrzeit":"Thu, 01 Jul 2021 13:19:38 GMT","Herzschlag":"87","Sauerstoff":"","Emotion":""},{"Uhrzeit":"Thu, 01 Jul 2021 13:19:38 GMT","Herzschlag":"87","Sauerstoff":"","Emotion":""},{"Uhrzeit":"Thu, 01 Jul 2021 13:19:39 GMT","Herzschlag":"87","Sauerstoff":"","Emotion":""},{"Uhrzeit":"Thu, 01 Jul 2021 13:19:39 GMT","Herzschlag":"86","Sauerstoff":"","Emotion":""},{"Uhrzeit":"Thu, 01 Jul 2021 13:19:39 GMT","Herzschlag":"86","Sauerstoff":"","Emotion":""},{"Uhrzeit":"Thu, 01 Jul 2021 13:19:39 GMT","Herzschlag":"86","Sauerstoff":"","Emotion":""},{"Uhrzeit":"Thu, 01 Jul 2021 13:19:40 GMT","Herzschlag":"86","Sauerstoff":"","Emotion":""},{"Uhrzeit":"Thu, 01 Jul 2021 13:19:40 GMT","Herzschlag":"86","Sauerstoff":"","Emotion":""},{"Uhrzeit":"Thu, 01 Jul 2021 13:19:40 GMT","Herzschlag":"86","Sauerstoff":"","Emotion":""}]